<?xml version="1.0" encoding="utf-8"?>
<!--Do not comment in <GridView></GridView> node,please comment here.
-->
<GridView>
  <Property OrderBy="ContainerNo" />
  <Columns>
    <FieldName>Port</FieldName>
    <FieldType>String</FieldType>
    <FieldWidth>100</FieldWidth>
    <Order>1</Order>
    <Visible>true</Visible>
    <EnglishTitle>Port</EnglishTitle>
    <ChineseTitle>Port</ChineseTitle>
  </Columns>
  <!--1_BoxDischarge-->
  <Columns>
    <FieldName>20BXD</FieldName>
    <FieldType>Intger</FieldType>
    <FieldWidth>50</FieldWidth>
    <Order>2</Order>
    <Visible>true</Visible>
    <EnglishTitle>20</EnglishTitle>
    <ChineseTitle>20</ChineseTitle>
  </Columns>
  <Columns>
    <FieldName>40BXD</FieldName>
    <FieldType>Intger</FieldType>
    <FieldWidth>50</FieldWidth>
    <Order>3</Order>
    <Visible>true</Visible>
    <EnglishTitle>40</EnglishTitle>
    <ChineseTitle>40</ChineseTitle>
  </Columns>
  <Columns>
    <FieldName>45BXD</FieldName>
    <FieldType>Intger</FieldType>
    <FieldWidth>50</FieldWidth>
    <Order>4</Order>
    <Visible>true</Visible>
    <EnglishTitle>50</EnglishTitle>
    <ChineseTitle>50</ChineseTitle>
  </Columns>
  <!--2_GateOut-->
  <Columns>
    <FieldName>20GTO</FieldName>
    <FieldType>Intger</FieldType>
    <FieldWidth>50</FieldWidth>
    <Order>5</Order>
    <Visible>true</Visible>
    <EnglishTitle>20</EnglishTitle>
    <ChineseTitle>20</ChineseTitle>
  </Columns>
  <Columns>
    <FieldName>40GTO</FieldName>
    <FieldType>Intger</FieldType>
    <FieldWidth>50</FieldWidth>
    <Order>6</Order>
    <Visible>true</Visible>
    <EnglishTitle>40</EnglishTitle>
    <ChineseTitle>40</ChineseTitle>
  </Columns>
  <Columns>
    <FieldName>45GTO</FieldName>
    <FieldType>Intger</FieldType>
    <FieldWidth>50</FieldWidth>
    <Order>7</Order>
    <Visible>true</Visible>
    <EnglishTitle>50</EnglishTitle>
    <ChineseTitle>50</ChineseTitle>
  </Columns>
  <!--3_DPI State= AV Or null-->
  <Columns>
    <FieldName>20DPI</FieldName>
    <FieldType>Intger</FieldType>
    <FieldWidth>50</FieldWidth>
    <Order>8</Order>
    <Visible>true</Visible>
    <EnglishTitle>20</EnglishTitle>
    <ChineseTitle>20</ChineseTitle>
  </Columns>
  <Columns>
    <FieldName>40DPI</FieldName>
    <FieldType>Intger</FieldType>
    <FieldWidth>50</FieldWidth>
    <Order>9</Order>
    <Visible>true</Visible>
    <EnglishTitle>40</EnglishTitle>
    <ChineseTitle>40</ChineseTitle>
  </Columns>
  <Columns>
    <FieldName>45DPI</FieldName>
    <FieldType>Intger</FieldType>
    <FieldWidth>50</FieldWidth>
    <Order>10</Order>
    <Visible>true</Visible>
    <EnglishTitle>50</EnglishTitle>
    <ChineseTitle>50</ChineseTitle>
  </Columns>
  <!--4_DPI State= DM-->
  <Columns>
    <FieldName>20DpiAv</FieldName>
    <FieldType>Intger</FieldType>
    <FieldWidth>50</FieldWidth>
    <Order>11</Order>
    <Visible>true</Visible>
    <EnglishTitle>20</EnglishTitle>
    <ChineseTitle>20</ChineseTitle>
  </Columns>
  <Columns>
    <FieldName>40DpiAv</FieldName>
    <FieldType>Intger</FieldType>
    <FieldWidth>50</FieldWidth>
    <Order>12</Order>
    <Visible>true</Visible>
    <EnglishTitle>40</EnglishTitle>
    <ChineseTitle>40</ChineseTitle>
  </Columns>
  <Columns>
    <FieldName>45DpiAv</FieldName>
    <FieldType>Intger</FieldType>
    <FieldWidth>50</FieldWidth>
    <Order>13</Order>
    <Visible>true</Visible>
    <EnglishTitle>50</EnglishTitle>
    <ChineseTitle>50</ChineseTitle>
  </Columns>
  <!--5_DPO -->
  <Columns>
    <FieldName>20DPO</FieldName>
    <FieldType>Intger</FieldType>
    <FieldWidth>50</FieldWidth>
    <Order>14</Order>
    <Visible>true</Visible>
    <EnglishTitle>20</EnglishTitle>
    <ChineseTitle>20</ChineseTitle>
  </Columns>
  <Columns>
    <FieldName>40DPO</FieldName>
    <FieldType>Intger</FieldType>
    <FieldWidth>50</FieldWidth>
    <Order>15</Order>
    <Visible>true</Visible>
    <EnglishTitle>40</EnglishTitle>
    <ChineseTitle>40</ChineseTitle>
  </Columns>
  <Columns>
    <FieldName>45DPO</FieldName>
    <FieldType>Intger</FieldType>
    <FieldWidth>50</FieldWidth>
    <Order>16</Order>
    <Visible>true</Visible>
    <EnglishTitle>50</EnglishTitle>
    <ChineseTitle>50</ChineseTitle>
  </Columns>
  <!--6_GTI or BXL -->
  <Columns>
    <FieldName>20GtiBxl</FieldName>
    <FieldType>Intger</FieldType>
    <FieldWidth>50</FieldWidth>
    <Order>17</Order>
    <Visible>true</Visible>
    <EnglishTitle>20</EnglishTitle>
    <ChineseTitle>20</ChineseTitle>
  </Columns>
  <Columns>
    <FieldName>40GtiBxl</FieldName>
    <FieldType>Intger</FieldType>
    <FieldWidth>50</FieldWidth>
    <Order>18</Order>
    <Visible>true</Visible>
    <EnglishTitle>40</EnglishTitle>
    <ChineseTitle>40</ChineseTitle>
  </Columns>
  <Columns>
    <FieldName>45GtiBxl</FieldName>
    <FieldType>Intger</FieldType>
    <FieldWidth>50</FieldWidth>
    <Order>19</Order>
    <Visible>true</Visible>
    <EnglishTitle>50</EnglishTitle>
    <ChineseTitle>50</ChineseTitle>
  </Columns>
</GridView>